pybtexris/__init__.py
pybtexris/data/types.csv
pybtexris/parsers.py
pybtexris-0.1.2.dist-info/entry_points.txt
pybtexris-0.1.2.dist-info/LICENSE
pybtexris-0.1.2.dist-info/WHEEL
pybtexris-0.1.2.dist-info/METADATA
pybtexris-0.1.2.dist-info/RECORD
